{
  "unversionedId": "tutorials/scaler",
  "id": "version-v1.5/tutorials/scaler",
  "title": "Modify Replicas",
  "description": "This article introduces how KubeVela adjusts the number of application copies.",
  "source": "@site/versioned_docs/version-v1.5/tutorials/scaler.md",
  "sourceDirName": "tutorials",
  "slug": "/tutorials/scaler",
  "permalink": "/docs/tutorials/scaler",
  "draft": false,
  "tags": [],
  "version": "v1.5",
  "lastUpdatedBy": "Author",
  "lastUpdatedAt": 1539502055,
  "formattedLastUpdatedAt": "Oct 14, 2018",
  "frontMatter": {
    "title": "Modify Replicas",
    "description": "This article introduces how KubeVela adjusts the number of application copies."
  }
}